thematic_structurizer/__init__.py
thematic_structurizer/main.py
thematic_structurizer/prompts.py
thematic_structurizer-2025.12.21114407.dist-info/METADATA
thematic_structurizer-2025.12.21114407.dist-info/WHEEL
thematic_structurizer-2025.12.21114407.dist-info/top_level.txt
thematic_structurizer-2025.12.21114407.dist-info/RECORD
