Metadata-Version: 2.4
Name: thematic-structurizer
Version: 2025.12.21114407
Summary: A new package would process user-provided text input related to historical or thematic content—such as summaries, descriptions, or analyses of topics like persuasion techniques from antiquity—and retu
Author-email: thematic-structurizer <hi@eugene.plus>
License: MIT
Project-URL: Homepage, https://github.com/chigwell/thematic-structurizer
Requires-Python: >=3.9
Requires-Dist: langchain-llm7>=0.0.0
Requires-Dist: llmatch-messages>=0.0.0
Requires-Dist: langchain-core>=0.3.0
